{
  "version": "0.3.14-fixed",
  "steps": [
    {
      "tag": "CreateModel",
      "model": "Location"
    },
    {
      "tag": "CreateField",
      "model": "Location",
      "field": "Rest",
      "type": "Rest",
      "arity": "Required"
    },
    {
      "tag": "CreateDirective",
      "location": {
        "path": {
          "tag": "Field",
          "model": "Location",
          "field": "Rest"
        },
        "directive": "relation"
      }
    },
    {
      "tag": "CreateArgument",
      "location": {
        "tag": "Directive",
        "path": {
          "tag": "Field",
          "model": "Location",
          "field": "Rest"
        },
        "directive": "relation"
      },
      "argument": "fields",
      "value": "[restId]"
    },
    {
      "tag": "CreateArgument",
      "location": {
        "tag": "Directive",
        "path": {
          "tag": "Field",
          "model": "Location",
          "field": "Rest"
        },
        "directive": "relation"
      },
      "argument": "references",
      "value": "[id]"
    },
    {
      "tag": "CreateField",
      "model": "Location",
      "field": "restId",
      "type": "Int",
      "arity": "Required"
    },
    {
      "tag": "CreateDirective",
      "location": {
        "path": {
          "tag": "Field",
          "model": "Location",
          "field": "restId"
        },
        "directive": "unique"
      }
    },
    {
      "tag": "CreateField",
      "model": "Location",
      "field": "latitude",
      "type": "Float",
      "arity": "Required"
    },
    {
      "tag": "CreateField",
      "model": "Location",
      "field": "longitude",
      "type": "Float",
      "arity": "Required"
    },
    {
      "tag": "CreateField",
      "model": "Rest",
      "field": "location",
      "type": "Location",
      "arity": "Required"
    }
  ]
}